general_validator/__init__.py
general_validator/base.py
general_validator/check.py
general_validator/engine.py
general_validator/inspect.py
general_validator/logger.py
general_validator/validate.py
general_validator-1.7.0.dist-info/LICENSE
general_validator-1.7.0.dist-info/METADATA
general_validator-1.7.0.dist-info/WHEEL
general_validator-1.7.0.dist-info/RECORD
