Metadata-Version: 2.3
Name: general-validator
Version: 1.7.0
Summary: General-Validator is a universal batch data validator.
License: The MIT License (MIT)
Author: Devin
Author-email: zhangchuzhao@dingtalk.com
Requires-Python: >=3.6
Classifier: License :: Other/Proprietary License
Classifier: Programming Language :: Python :: 3
Classifier: Programming Language :: Python :: 3.6
Classifier: Programming Language :: Python :: 3.7
Classifier: Programming Language :: Python :: 3.8
Classifier: Programming Language :: Python :: 3.9
Classifier: Programming Language :: Python :: 3.10
Classifier: Programming Language :: Python :: 3.11
Classifier: Programming Language :: Python :: 3.12
Classifier: Programming Language :: Python :: 3.13
Provides-Extra: docs
Provides-Extra: test
Requires-Dist: colorama (==0.4.1)
Requires-Dist: colorlog (==4.0.2)
Requires-Dist: mkdocs-material (>=9.0.0) ; extra == "docs"
Requires-Dist: pytest (>=6.0.0) ; extra == "test"
Requires-Dist: pytest-cov (>=3.0.0) ; extra == "test"
Requires-Dist: pytest-mock (>=3.0.0) ; extra == "test"
